junoaccessmanager/__init__.py
junoaccessmanager/api/__init__.py
junoaccessmanager/api/user.py
JunoAccessManager-1.1.2.dist-info/LICENSE
JunoAccessManager-1.1.2.dist-info/METADATA
JunoAccessManager-1.1.2.dist-info/WHEEL
JunoAccessManager-1.1.2.dist-info/top_level.txt
JunoAccessManager-1.1.2.dist-info/RECORD
