Metadata-Version: 2.1
Name: JunoAccessManager
Version: 1.1.2
Summary: 租户接入
Author: Yuhui.Wang
Author-email: wangyuhui341@163.com
Classifier: Programming Language :: Python :: 3
Classifier: License :: OSI Approved :: MIT License
Classifier: Operating System :: OS Independent
Requires-Python: >=3.6
License-File: LICENSE
Requires-Dist: backports.tarfile
Requires-Dist: certifi
Requires-Dist: charset-normalizer
Requires-Dist: docutils
Requires-Dist: idna
Requires-Dist: importlib-metadata
Requires-Dist: jaraco.classes
Requires-Dist: jaraco.context
Requires-Dist: jaraco.functools
Requires-Dist: keyring
Requires-Dist: markdown-it-py
Requires-Dist: mdurl
Requires-Dist: more-itertools
Requires-Dist: nh3
Requires-Dist: pkginfo
Requires-Dist: pulsar-client
Requires-Dist: Pygments
Requires-Dist: pywin32-ctypes
Requires-Dist: readme-renderer
Requires-Dist: requests
Requires-Dist: requests-toolbelt
Requires-Dist: rfc3986
Requires-Dist: rich
Requires-Dist: twine
Requires-Dist: typing-extensions
Requires-Dist: urllib3
Requires-Dist: zipp
